{
  "id": 354,
  "title": "Псалом 67",
  "content": "Да воскреснет Бог, и расточатся врази Еro, и да бежат от лица Его ненавидящии Его. Яко исчезает дым, да исчезнут, яко тает воск от лица огня, тако да погибнут грешницы от лица Божия, а праведницы да возвеселятся, да возрадуются пред Богом, да насладятся в веселии. Воспойте Богу, пойте имени Его, путесотворите возшедшему на запады. Господь имя Ему, и радуйтеся пред Ним. Да смятутся от лица Его, Отца сирых и Судии вдовиц: Бог в месте святем Своем. Бог вселяет единомысленныя в дом, изводя окованныя мужеством, такожде преогорчевающыя живущыя во гробех. Боже, внегда исходити Тебе пред людьми Твоими, внегда мимоходити Тебе в пустыни, земля потрясеся, ибо небеса кануша от лица Бога Синаина, от лица Бога Израилева. Дождь волен отлучиши, Боже, достоянию Твоему и изнеможе, Ты же совершил еси е. Животная Твоя живут на ней, уготовал еси благостию Твоею нищему, Боже. Господь даст глагол благовествующым силою многою. Царь сил возлюбленнаго, красотою дому разделити корысти. Аще поспите посреде предел, криле голубине посребрене, и междорамия ея в блещании злата. Внегда разнствит Небесный цари на ней, оснежатся в Селмоне. Гора Божия, гора тучная, гора усыренная, гора тучная. Вскую непщуете горы усыренныя? Гора, юже благоволи Бог жити в ней, ибо Господь вселится до конца. Колесница Божия тмами тем, тысяща гобзующих, Господь в них в Синаи во святем. Возшел еси на высоту, пленил еси плен, приял еси даяния в человецех, ибо не покаряющыяся, еже вселитися. Господь Бог благословен, благословен Господь день дне, поспешит нам Бог спасений наших. Бог наш, Бог еже спасати, и Господня, Господня исходища смертная. Обаче Бог сокрушит главы врагов Своих, верх влас преходящих в прегрешениих своих. Рече Господь: от Васана обращу, обращу во глубинах морских. Яко да омочится нога твоя в крови, язык пес твоих, от враг от него. Видена быша шествия Твоя, Боже, шествия Бога моего Царя, иже во святем, предвариша князи близ поющих, посреде дев тимпанниц. В церквах благословите Бога, Господа от источник Израилевых. Тамо Вениамин юнейший во ужасе, книзи Иудовы владыки их, князи Завулони, князи Неффалимли. Заповеждь, Боже, силою Твоею, укрепи, Боже, сие, еже соделал еси в нас. От храма Твоего во Иерусалим Тебе принесут царие дары. Запрети зверем тростным, сонм юнец в юницах людских, еже затворити искушенныя сребром, расточи языки хотящыя бранем. Приидут молитвенницы от Египта, Ефиопиа предварит руку свою к Богу. Царства земная, пойте Богу, воспойте Господеви, возшедшему на Небо небесе на востоки, се даст гласу Своему глас силы. Дадите славу Богови, на Израили велелепота Его, и сила Его на облацех. Дивен Бог во святых Своих, Бог Израилев: Той даст силу и державу людем Своим, благословен Бог.",
  "originalUrl": "https://www.molitvoslov.com/text805.htm",
  "createdAt": "2025-09-20T21:23:11.962Z",
  "updatedAt": "2025-09-22T11:39:17.014Z",
  "url": "psalom-67",
  "contentModern": "Да воскреснет Бог, и расточатся врази Еro, и да бежат от лица Его ненавидящии Его. как исчезает дым, да исчезнут, как тает воск от лица огня, тако да погибнут грешницы от лица Божие, а праведницы да возвеселятся, да возрадуются пред Богом, да насладятся в веселии. Воспойте Богу, пойте имени Его, путесотворите возшедшему на запады. Господь имя Ему, и радуйтеся пред Ним. Да смятутся от лица Его, Отца сирых и Судии вдовиц: Бог в месте святем Своем. Бог вселяет единомысленние в дом, изводя окованние мужеством, такожде преогорчевающие живущие во гробех. Боже, внегда исходити Тебе пред людьми Твоими, внегда мимоходити Тебе в пустыни, земля потрясеся, ибо небеса кануша от лица Бога Синаина, от лица Бога Израилева. Дождь волен отлучиши, Боже, достоянию Твоему и изнеможе, Ты же совершил есть е. Животная Твоя живут на ней, уготовал есть благостию Твоею нищему, Боже. Господь даст глагол благовествующым силою многою. Царь сил возлюбленнаго, красотою дому разделити корысти. если поспите посреде предел, криле голубине посребрене, и междорамие ея в блещании злата. Внегда разнствит Небесный цари на ней, оснежатся в Селмоне. Гора Божие, гора тучная, гора усыренная, гора тучная. Вскую непщуете горы усыренние? Гора, юже благоволи Бог жити в ней, ибо Господь вселится до конца. Колесница Божие тмами тем, тысяща гобзующих, Господь в них в Синаи во святем. Возшел есть на высоту, пленил есть плен, приял есть даяние в человецех, ибо не покаряющыяся, еже вселитися. Господь Бог благословен, благословен Господь день дне, поспешит нам Бог спасений наших. Бог наш, Бог еже спасати, и Господня, Господня исходища смертная. Обаче Бог сокрушит главы врагов Своих, верх влас преходящих в прегрешениих своих. Рече Господь: от Васана обращу, обращу во глубинах морских. как да омочится нога твоя в крови, язык пес твоих, от враг от него. Видена быша шествие Твоя, Боже, шествие Бога моего Царя, иже во святем, предвариша князи близ поющих, посреде дев тимпанниц. В церквах благословите Бога, Господа от источник Израилевых. Тамо Вениамин юнейший во ужасе, книзи Иудовы владыки их, князи Завулони, князи Неффалимли. Заповеждь, Боже, силою Твоею, укрепи, Боже, сие, еже соделал есть в нас. От храма Твоего во Иерусалим Тебе принесут царие дары. Запрети зверем тростным, сонм юнец в юницах людских, еже затворити искушенние сребром, расточи языки хотящие бранем. Приидут молитвенницы от Египта, Ефиопиа предварит руку свою к Богу. Царства земная, пойте Богу, воспойте Господеви, возшедшему на Небо небесе на востоки, се даст гласу Своему глас силы. Дадите славу Богови, на Израили велелепота Его, и сила Его на облацех. Дивен Бог во святых Своих, Бог Израилев: Той даст силу и державу людем Своим, благословен Бог.",
  "summary": {
    "text": "Православная молитва для духовного чтения, укрепления веры и общения с Богом.",
    "tags": [
      "общая молитва",
      "псалтирь",
      "православные молитвы",
      "молитвенник",
      "духовность",
      "вера"
    ]
  },
  "explanation": "Эта молитва помогает верующему в духовном общении с Богом, укреплении веры и получении благодатной помощи в различных жизненных обстоятельствах.",
  "relatedPrayers": [
    {
      "id": 5,
      "title": "Благодарение за всякое благодеяние Божие",
      "url": "blagodarenie-za-vsyakoe-blagodeyanie-bozhie",
      "commonTags": [
        "общая молитва"
      ]
    },
    {
      "id": 14,
      "title": "Благодарственные молитвы по Святом Причащении - ко святому причащению",
      "url": "blagodarstvennye-molitvy-po-svyatom-prichaschenii",
      "commonTags": [
        "общая молитва"
      ]
    },
    {
      "id": 472,
      "title": "Чин чтения 12-ти псалмов",
      "url": "chin-chteniya-12-ti-psalmov",
      "commonTags": [
        "общая молитва"
      ]
    },
    {
      "id": 346,
      "title": "Чин молитвеннаго утешения сродников живот свой самовольне скончавшаго",
      "url": "chin-molitvennago-utesheniya-srodnikov-zhivot-svoy-samovolne-skonchavshago",
      "commonTags": [
        "общая молитва"
      ]
    },
    {
      "id": 308,
      "title": "Cвятителю Нектарию Эгинскому",
      "url": "cvyatitelyu-nektariyu-eginskomu",
      "commonTags": [
        "общая молитва"
      ]
    }
  ],
  "seoOptimized": {
    "title": "Псалом 67",
    "description": "Православная молитва для духовного чтения, укрепления веры и общения с Богом.",
    "keywords": [
      "общая молитва",
      "псалтирь",
      "православные молитвы",
      "молитвенник",
      "духовность",
      "вера"
    ],
    "canonicalUrl": "https://molitvy-dnya.ru/prayer/psalom-67",
    "structuredData": {
      "@type": "Article",
      "headline": "Псалом 67",
      "description": "Православная молитва для духовного чтения, укрепления веры и общения с Богом.",
      "keywords": "общая молитва, псалтирь, православные молитвы, молитвенник, духовность, вера",
      "articleBody": "Да воскреснет Бог, и расточатся врази Еro, и да бежат от лица Его ненавидящии Его. Яко исчезает дым, да исчезнут, яко тает воск от лица огня, тако да погибнут грешницы от лица Божия, а праведницы да возвеселятся, да возрадуются пред Богом, да насладятся в веселии. Воспойте Богу, пойте имени Его, путесотворите возшедшему на запады. Господь имя Ему, и радуйтеся пред Ним. Да смятутся от лица Его, Отца сирых и Судии вдовиц: Бог в месте святем Своем. Бог вселяет единомысленныя в дом, изводя окованныя мужеством, такожде преогорчевающыя живущыя во гробех. Боже, внегда исходити Тебе пред людьми Твоими, внегда мимоходити Тебе в пустыни, земля потрясеся, ибо небеса кануша от лица Бога Синаина, от лица Бога Израилева. Дождь волен отлучиши, Боже, достоянию Твоему и изнеможе, Ты же совершил еси е. Животная Твоя живут на ней, уготовал еси благостию Твоею нищему, Боже. Господь даст глагол благовествующым силою многою. Царь сил возлюбленнаго, красотою дому разделити корысти. Аще поспите посреде предел, криле голубине посребрене, и междорамия ея в блещании злата. Внегда разнствит Небесный цари на ней, оснежатся в Селмоне. Гора Божия, гора тучная, гора усыренная, гора тучная. Вскую непщуете горы усыренныя? Гора, юже благоволи Бог жити в ней, ибо Господь вселится до конца. Колесница Божия тмами тем, тысяща гобзующих, Господь в них в Синаи во святем. Возшел еси на высоту, пленил еси плен, приял еси даяния в человецех, ибо не покаряющыяся, еже вселитися. Господь Бог благословен, благословен Господь день дне, поспешит нам Бог спасений наших. Бог наш, Бог еже спасати, и Господня, Господня исходища смертная. Обаче Бог сокрушит главы врагов Своих, верх влас преходящих в прегрешениих своих. Рече Господь: от Васана обращу, обращу во глубинах морских. Яко да омочится нога твоя в крови, язык пес твоих, от враг от него. Видена быша шествия Твоя, Боже, шествия Бога моего Царя, иже во святем, предвариша князи близ поющих, посреде дев тимпанниц. В церквах благословите Бога, Господа от источник Израилевых. Тамо Вениамин юнейший во ужасе, книзи Иудовы владыки их, князи Завулони, князи Неффалимли. Заповеждь, Боже, силою Твоею, укрепи, Боже, сие, еже соделал еси в нас. От храма Твоего во Иерусалим Тебе принесут царие дары. Запрети зверем тростным, сонм юнец в юницах людских, еже затворити искушенныя сребром, расточи языки хотящыя бранем. Приидут молитвенницы от Египта, Ефиопиа предварит руку свою к Богу. Царства земная, пойте Богу, воспойте Господеви, возшедшему на Небо небесе на востоки, се даст гласу Своему глас силы. Дадите славу Богови, на Израили велелепота Его, и сила Его на облацех. Дивен Бог во святых Своих, Бог Израилев: Той даст силу и державу людем Своим, благословен Бог.",
      "inLanguage": "ru"
    }
  },
  "enhancedAt": "2025-09-22T11:39:17.014Z",
  "version": "2.0"
}