{
  "id": 77,
  "title": "Молитва идущего в церковь",
  "content": "Возвеселихся о рекших мне: в дом Господень пойдем. Аз же множеством милости Твоея, Господи, вниду в дом Твой, поклонюся ко храму святому Твоему в страсе Твоем. Господи, настави мя правдою Твоею, враг моих ради исправи пред Тобою путь мой; да без преткновения прославлю Едино Божество, Отца и Сына и Святаго Духа, ныне и присно и во веки веков. Аминь.",
  "originalUrl": "https://www.molitvoslov.com/text524.htm",
  "createdAt": "2025-09-20T21:13:09.580Z",
  "updatedAt": "2025-09-22T03:50:11.439Z",
  "url": "molitva-iduschego-v-tserkov",
  "contentModern": "Возвеселихся о рекших мне: в дом Господень поидем. Аз же множеством милости Твоея, Господи, вниду в дом Твои, поклонюся ко храму святому Твоему в страсе Твоем. Господи, настави меня правдою Твоею, враг моих ради исправи пред Тобою путь мои; да без преткновения прославлю Едино Божество, Отца и Сына и Святаго Духа, ныне и всегда и во веки веков. Аминь.",
  "summary": {
    "text": "Краткая молитва.",
    "tags": [
      "Господу"
    ]
  }
}